{
  "schemaVersion": 1,
  "originalFileName": "Commando.ay",
  "sourceFormat": "AY",
  "sourceSha256": "51e49d0413be6c557ef5e2696cfc051dfcd0931bbbfba8029c90ebf69dd6d629",
  "sourceByteLength": 3205,
  "subsong": 1,
  "chipType": "AY",
  "chipClockHz": 1773400,
  "frameRateHz": 50,
  "channelLayout": "ABC",
  "runtimeMode": "convert",
  "runtimeFormat": "YM6",
  "runtimeSha256": "6db79e4e1e0246b4faf622652283326e5a38b0bba172f911fb0dcca0d494dc28",
  "runtimeByteLength": 201714,
  "frameCount": 12600,
  "durationSeconds": 252,
  "durationSource": "source",
  "durationOverride": null,
  "waveformSha256": "dab47f5ff010155a012d1e2fdcf18d7e54e0fb64223266b39f120016c904bd83",
  "trackerConversion": null,
  "preparationTool": "zxmusicfm-content-v1",
  "engine": {
    "name": "ym2149-rs",
    "commit": "b3096aac0dcab6dd1d82c0209f579761943aadc6"
  }
}
